easydpl/__init__.py
easydpl/_modidx.py
easydpl/_nbdev.py
easydpl/_pytorch_doc.py
easydpl/basics.py
easydpl/collab.py
easydpl/distributed.py
easydpl/fp16_utils.py
easydpl/imports.py
easydpl/interpret.py
easydpl/layers.py
easydpl/learner.py
easydpl/losses.py
easydpl/metric.py
easydpl/metrics.py
easydpl/optimizer.py
easydpl/patches.cpython-311-x86_64-linux-gnu.so
easydpl/test_utils.py
easydpl/torch_basics.py
easydpl/torch_core.py
easydpl/torch_imports.py
easydpl/callback/__init__.py
easydpl/callback/all.py
easydpl/callback/azureml.py
easydpl/callback/captum.py
easydpl/callback/channelslast.py
easydpl/callback/comet.py
easydpl/callback/core.py
easydpl/callback/data.py
easydpl/callback/fp16.py
easydpl/callback/hook.py
easydpl/callback/mixup.py
easydpl/callback/preds.py
easydpl/callback/progress.py
easydpl/callback/rnn.py
easydpl/callback/schedule.py
easydpl/callback/tensorboard.py
easydpl/callback/tracker.py
easydpl/callback/training.py
easydpl/callback/wandb.py
easydpl/data/__init__.py
easydpl/data/all.py
easydpl/data/block.py
easydpl/data/core.py
easydpl/data/download_checks.py
easydpl/data/external.py
easydpl/data/load.py
easydpl/data/transforms.py
easydpl/medical/__init__.py
easydpl/medical/imaging.py
easydpl/medical/text.py
easydpl/tabular/__init__.py
easydpl/tabular/all.py
easydpl/tabular/core.py
easydpl/tabular/data.py
easydpl/tabular/learner.py
easydpl/tabular/model.py
easydpl/text/__init__.py
easydpl/text/all.py
easydpl/text/core.py
easydpl/text/data.py
easydpl/text/learner.py
easydpl/text/models/__init__.py
easydpl/text/models/awdlstm.py
easydpl/text/models/core.py
easydpl/vision/__init__.py
easydpl/vision/all.py
easydpl/vision/augment.py
easydpl/vision/core.py
easydpl/vision/data.py
easydpl/vision/gan.py
easydpl/vision/learner.py
easydpl/vision/utils.py
easydpl/vision/widgets.py
easydpl/vision/models/__init__.py
easydpl/vision/models/all.py
easydpl/vision/models/tvm.py
easydpl/vision/models/unet.py
easydpl/vision/models/xresnet.py
easydpl-0.0.9.dist-info/licenses/LICENSE
easydpl-0.0.9.dist-info/METADATA
easydpl-0.0.9.dist-info/WHEEL
easydpl-0.0.9.dist-info/entry_points.txt
easydpl-0.0.9.dist-info/top_level.txt
easydpl-0.0.9.dist-info/RECORD
