Metadata-Version: 2.4
Name: easydpl
Version: 0.0.9
Summary: easydpl simplifies training fast and accurate neural nets using modern best practices
Home-page: https://github.com/easydpl/easydpl
Author: Jeremy Howard, Sylvain Gugger, and contributors
Author-email: info@fast.ai
License: Apache Software License 2.0
Keywords: easydpl,deep learning,machine learning
Classifier: Development Status :: 5 - Production/Stable
Classifier: Intended Audience :: Developers
Classifier: License :: OSI Approved :: Apache Software License
Classifier: Natural Language :: English
Classifier: Programming Language :: Python :: 3.8
Classifier: Programming Language :: Python :: 3.9
Classifier: Programming Language :: Python :: 3.10
Requires-Python: >=3.8
License-File: LICENSE
Requires-Dist: pip
Requires-Dist: packaging
Requires-Dist: fastdownload<2,>=0.0.5
Requires-Dist: fastcore<1.6,>=1.5.29
Requires-Dist: torchvision>=0.11
Requires-Dist: matplotlib
Requires-Dist: pandas
Requires-Dist: requests
Requires-Dist: pyyaml
Requires-Dist: fastprogress>=0.2.4
Requires-Dist: pillow>=9.0.0
Requires-Dist: scikit-learn
Requires-Dist: scipy
Requires-Dist: spacy<4
Requires-Dist: packaging
Requires-Dist: numpy<2
Requires-Dist: torch<2.2,>=1.10
Provides-Extra: dev
Dynamic: author
Dynamic: author-email
Dynamic: classifier
Dynamic: description
Dynamic: description-content-type
Dynamic: home-page
Dynamic: keywords
Dynamic: license
Dynamic: license-file
Dynamic: provides-extra
Dynamic: requires-dist
Dynamic: requires-python
Dynamic: summary
